{
    "$schema": "https://github.com/Blitz-BS/blitzCollection/schema_files_stream.json",
    "$id": "https://github.com/Blitz-BS/blitzCollection/schema_files_stream",
    "title": "CollectionStream",
    "description": "Import dossiers MyDOSManager",
    "type": "object",
    "properties": {
        "collectionCompanyReference": {
            "type": "string",
            "$comment": "reference of collection compagny - provided by Blitz | identifiant du cabinet - information fournie par Blitz"
        },
        "creditor": {
            "type": "array",
            "minItems": 1,
            "uniqueItems": true,
            "items": {
                "type": "object",
                "properties": {
                    "reference": {
                        "type": "string",
                        "$comment": "Creditor's reference - provided by Blitz | référence du créancier/client - information fournie par Blitz (correspond exactement au code client dans MGP)"
                    },
                    "contracts": {
                        "type": "array",
                        "minItems": 1,
                        "uniqueItems": true,
                        "items": {
                            "type": "object",
                            "properties": {
                                "reference": {
                                    "type": "string",
                                    "$comment": "contract's reference/number - provided by Blitz | référence du contract - information fournie par Blitz (correspond au contrat régissant les honoraires, ...)"
                                },
                                "files": {
                                    "type": "array",
                                    "minItems": 1,
                                    "uniqueItems": true,
                                    "items": {
                                        "type": "object",
                                        "properties": {
                                            "reference": {
                                                "type": "string",
                                                "$comment": "File's unique reference or invoice's reference if you cannot group debts by file | référence dossier, si vous ne pouvez pas grouper par dossier, il faut la référence de la créance avec uniquement cette créance dans le dossier"
                                            },
                                            "debts": {
                                                "type": "array",
                                                "minItems": 1,
                                                "uniqueItems": true,
                                                "items": {
                                                    "type": "object",
                                                    "properties": {
                                                        "reference": {
                                                            "type": "string",                    
                                                            "maxLength": 50,
                                                            "$comment": "invoice/debt reference | N° de facture/référence de créance"
                                                        },
                                                        "label": {
                                                            "type": "string",
                                                            "maxLength": 100,
                                                            "$comment": "Label or title of invoice | libellé de créance à voir l'évolution sur une énumération de type"
                                                        },
                                                        "debtType": {
                                                            "enum": ["Invoice"],
                                                            "$comment": "type of debt | type de créance (facture)"
                                                        },
                                                        "issueDate" : {
                                                            "type": "string",
                                                            "pattern": "^[1-9][0-9]{3}-[0-1][0-9]-[0-3][0-9]$",
                                                            "$comment": "Date format is YYYY-MM-dd | La date de la facture/créance au format AAAA-MM-JJ."
                                                        },
                                                        "dueDate": {
                                                            "type": "string",
                                                            "pattern": "^[1-9][0-9]{3}-[0-1][0-9]-[0-3][0-9]$",
                                                            "$comment": "Date format is YYYY-MM-dd | La date d'échéance de la facture/créance au format AAAA-MM-JJ."
                                                        },
                                                        "balance": {
                                                            "type": "number",
                                                            "minimum": -999999999999.99,
                                                            "maximum": 999999999999.99,
                                                            "$comment": "remaining amount with taxes | Solde restant dû en TTC"
                                                        },
                                                        "vatAmount": {
                                                            "type": "number",
                                                            "minimum": -999999999999.99,
                                                            "maximum": 999999999999.99,
                                                            "$comment": "VAT(+taxes) amount | Montant de TVA"
                                                        },                                              
                                                        "currencyCode": {
                                                            "type": "string",
                                                            "default": "EUR",
                                                            "minLength": 3,
                                                            "maxLength": 3,
                                                            "$comment": "Currency code (ISO 4217) | code devise de la créance."
                                                        },
                                                        "incidentals": {
                                                            "type": "array",
                                                            "items": {
                                                                "properties": {
                                                                "rate": {
                                                                    "type": "number"
                                                                },
                                                                "startDate": {
                                                                    "type": "string",
                                                                    "pattern": "^[1-9][0-9]{3}-[0-1][0-9]-[0-3][0-9]$",
                                                                    "$comment": "the date interest begins (the day after generates the first interests) | date de départ des intérêts (départ exclu)"
                                                                },
                                                                "amount": {
                                                                    "type": "number",
                                                                    "minimum": -999999999999.99,
                                                                    "maximum": 999999999999.99,
                                                                    "$comment": "incidental fees in debt's currency | Montant de l'accessoire en devise de la créance"
                                                                },
                                                                "incidentalsType": {
                                                                    "enum" : ["Interests", "Late payment fee"],                                                                    
                                                                    "$comment": "type of incidentals | type d'accessoires (intérêts, pénalité de retard)"
                                                                }
                                                            }
                                                            },
                                                            "contains": {
                                                                "oneOf": [
                                                                    {
                                                                        "type": "object",
                                                                        "properties": {
                                                                            "incidentalsType": { "const": "Interests" }
                                                                        },
                                                                        "required": ["incidentalsType", "rate", "startDate"]
                                                                    },
                                                                    { 
                                                                        "type": "object",
                                                                        "properties": {
                                                                            "not": {"incidentalsType": { "const": "Interests" }}
                                                                        },
                                                                        "required": ["incidentalsType", "amount"]
                                                                    }
                                                                ]
                                                            }
                                                        }
                                                    }
                                                },
                                                "required": ["reference", "label", "debtType", "issueDate", "dueDate", "balance", "vatAmount"],
                                                "$comment": "TVA requise pour l'édition des CI"
                                            },
                                            "parties": {
                                                "type": "array",
                                                "minItems": 1,
                                                "uniqueItems": true,
                                                "items": {
                                                    "type": "object",
                                                    "properties": {
                                                        "name": {
                                                            "type": "string",
                                                            "maxLength": 70,
                                                            "$comment": "name or company name | nom ou raison sociale"
                                                        },                                                        
                                                        "role": {
                                                            "enum": ["Debtor", "Codebtor", "Bailiff", "Administrator", "Attorney",  "Investigator", "Court"],
                                                            "$comment": "role of third-party | role du tiers, non-exhaustif pour l'instant"
                                                        },
                                                        "partyType": {
                                                            "enum": ["Legal person", "Natural person", "Joint ownership", "Household"],
                                                            "$comment": "type of third-party | type de tiers (personne morale, physique, indivision, foyer)"
                                                        },
                                                        "companyInfo": {
                                                            "type": "object",
                                                            "properties": {
                                                                "companyRegistrationNumber": {
                                                                    "type": "string",
                                                                    "maxLength": 21,
                                                                    "$comment": "CRN can be as long as 21 characters in India | SIRET/CRN"
                                                                },
                                                                "adress": {
                                                                        "type": "object",
                                                                        "properties": {
                                                                            "street": {
                                                                                "type": "string"
                                                                            },
                                                                            "city": {
                                                                                "type": "string"
                                                                            },
                                                                            "postalCode": {
                                                                                "type": "string"
                                                                            },
                                                                            "countryCode": {
                                                                                "type": "string",
                                                                                "default": "FRA",
                                                                                "maxLength": 3,
                                                                                "$comment": "3-lettered country code | Code pays (ISO 3166-1 alpha-3)"
                                                                            }
                                                                        },
                                                                        "required": ["street", "city", "postalCode"]
                                                                }
                                                            },
                                                            "anyOf": [
                                                                {"required": ["companyRegistrationNumber"]},
                                                                {"required": ["adress"]}
                                                            ],
                                                            "$comment": "Some countries only define legal person with an address | Certains pays définissent"
                                                        },
                                                        "contacts": {
                                                            "type": "array",
                                                            "items": {
                                                                "type": "object",
                                                                "properties": {
                                                                    "lastName": {
                                                                        "type": "string",
                                                                        "maxLength": 70
                                                                    },
                                                                    "firstName": {
                                                                        "type": "string",
                                                                        "maxLength": 70
                                                                    },
                                                                    "role": {
                                                                        "type": "string",
                                                                        "maxLength": 20,
                                                                        "$comment": "contact's role in the third-party | role du contact dans l'organisation tiers"
                                                                    },
                                                                    "phones": {
                                                                        "type": "array",
                                                                        "items": {
                                                                            "type": "string"
                                                                        },
                                                                        "$comment": "Phone numbers ordered by descending qualification | Numéro de téléphone par ordre décroissant de qualification"
                                                                    },
                                                                    "emails": {
                                                                        "type": "array",
                                                                        "items": {
                                                                            "type": "string"
                                                                        },
                                                                        "$comment": "email adresses ordered by descending qualification | adresses emails par ordre décroissant de qualification"
                                                                    },
                                                                    "languageCode": {
                                                                        "type": "string",
                                                                        "default": "fra",
                                                                        "minLength": 3,
                                                                        "maxLength": 3,
                                                                        "$comment": "contact's language code (ISO 639-3) | Code langue du contact (ISO 639-3)"
                                                                    },
                                                                    "adresses": {
                                                                        "type": "array",
                                                                        "items": {
                                                                            "type": "object",
                                                                            "properties": {
                                                                                "street": {
                                                                                    "type": "string"
                                                                                },
                                                                                "city": {
                                                                                    "type": "string"
                                                                                },
                                                                                "postalCode": {
                                                                                    "type": "string"
                                                                                },
                                                                                "countryCode": {
                                                                                    "type": "string",
                                                                                    "default": "FRA",
                                                                                    "maxLength": 3,
                                                                                    "$comment": "3-lettered country code | Code pays (ISO 3166-1 alpha-3)"
                                                                                }
                                                                            },
                                                                            "required": ["street", "city", "postalCode"]
                                                                        }
                                                                    }
                                                                },
                                                                "required": ["lastName", "firstName"]
                                                            }
                                                        },
                                                        "bankInfo": {
                                                            "type": "object",
                                                            "properties": {
                                                                "iban": {
                                                                    "type": "string",
                                                                    "maxLength": 45
                                                                },
                                                                "swiftCode": {
                                                                    "type": "string",
                                                                    "maxLength": 15,
                                                                    "$comment": "BIC"
                                                                },
                                                                "bank": {
                                                                    "type": "string",
                                                                    "maxLength": 40,
                                                                    "$comment": "Domiciliation"
                                                                },
                                                                "name": {
                                                                    "type": "string",
                                                                    "maxLength": 50,
                                                                    "$comment": "Nom du titulaire"
                                                                },
                                                                "bankCode": {
                                                                    "type": "string",
                                                                    "maxLength": 5,
                                                                    "$comment": "Code banque"
                                                                },
                                                                "sortCode": {
                                                                    "type": "string",
                                                                    "maxLength": 10,
                                                                    "$comment": "Code guichet"
                                                                },
                                                                "accountNumber": {
                                                                    "type": "string",
                                                                    "maxLength": 11
                                                                },
                                                                "key": {
                                                                    "type": "string",
                                                                    "maxLength": 2,
                                                                    "$commment": "Clé RIB/contrôle de l'IBAN"
                                                                }
                                                            },
                                                            "required": ["name"],
                                                            "anyOf": [
                                                                {"required": ["iban"]},
                                                                {"required": ["swiftCode", "accountNumber"]}
                                                            ],
                                                            "$comment": "Coordonnées bancaires"
                                                        }
                                                    },
                                                    "required": ["name", "role", "partyType"],
                                                    "if" : {
                                                        "not": {
                                                            "partyType": {"const": "Natural person"}
                                                        }
                                                    },
                                                    "then": {
                                                        "required": ["companyInfo"]
                                                    }
                                                }
                                            }
                                        }
                                    },
                                    "required": ["reference", "debts", "parties"],
                                    "contains": {
                                        "type": "object",
                                        "properties": {
                                            "role": { "const": "Debtor" }
                                        },
                                        "$comment": "A file is always linked to a debtor | un dossier est forcément lié à un débiteur"
                                    }
                                }
                            }
                        },
                        "required": ["reference", "files"]
                    }
                }
            },
            "required": ["reference", "contracts"],
            "$comment": "creditor/credit manager/customer"
        }
    },
    "required": ["collectionCompanyReference", "creditor"]
}